randomizer/__init__.py
randomizer/main.py
py_randomizer-0.0.3.dist-info/LICENSE
py_randomizer-0.0.3.dist-info/METADATA
py_randomizer-0.0.3.dist-info/WHEEL
py_randomizer-0.0.3.dist-info/top_level.txt
py_randomizer-0.0.3.dist-info/RECORD
