Metadata-Version: 2.1
Name: py-randomizer
Version: 0.0.3
Summary: A small library that simplifies randomly selecting things from lists.
Home-page: https://github.com/jessypeck/randomizer
Author: Jessica Peck
Author-email: jessypeck@gmail.com
License: UNKNOWN
Platform: UNKNOWN
Classifier: Programming Language :: Python :: 3
Classifier: License :: OSI Approved :: MIT License
Classifier: Operating System :: OS Independent
Requires-Python: >=3.6
